tradescope_client/__init__.py
tradescope_client/ts_client.py
tradescope_client/ts_rest_client.py
tradescope_client-2024.4.dist-info/LICENSE
tradescope_client-2024.4.dist-info/METADATA
tradescope_client-2024.4.dist-info/WHEEL
tradescope_client-2024.4.dist-info/entry_points.txt
tradescope_client-2024.4.dist-info/top_level.txt
tradescope_client-2024.4.dist-info/RECORD
