Metadata-Version: 2.1
Name: tradescope-client
Version: 2024.4
Summary: Tradescope - Client scripts
Author: KhulnaSoft Team
Author-email: KhulnaSoft Team <info@khulnasoft.com>
License: GPLv3
Project-URL: Homepage, https://github.com/khulnasoft/tradescope
Project-URL: Documentation, https://tradescope.io
Project-URL: Bug Tracker, https://github.com/khulnasoft/tradescope/issues
Classifier: Environment :: Console
Classifier: Intended Audience :: Science/Research
Classifier: License :: OSI Approved :: GNU General Public License v3 (GPLv3)
Classifier: Programming Language :: Python :: 3.9
Classifier: Programming Language :: Python :: 3.10
Classifier: Programming Language :: Python :: 3.11
Classifier: Programming Language :: Python :: 3.12
Classifier: Operating System :: MacOS
Classifier: Operating System :: Unix
Classifier: Topic :: Office/Business :: Financial :: Investment
Requires-Python: >=3.9
License-File: LICENSE
Requires-Dist: requests >=2.26.0
Requires-Dist: python-rapidjson >=1.0
